aiofastforward.py
aiofastforward-0.0.26.dist-info/METADATA
aiofastforward-0.0.26.dist-info/WHEEL
aiofastforward-0.0.26.dist-info/licenses/LICENSE
aiofastforward-0.0.26.dist-info/RECORD
