Metadata-Version: 2.1
Name: aiofastforward
Version: 0.0.26
Summary: Fast-forward time in asyncio Python by patching loop.time, loop.call_later, loop.call_at, and asyncio.sleep
Project-URL: Homepage, https://github.com/michalc/aiofastforward
Author-email: Michal Charemza <michal@charemza.name>
License-Expression: MIT
License-File: LICENSE
Classifier: Framework :: AsyncIO
Classifier: License :: OSI Approved :: MIT License
Classifier: Operating System :: OS Independent
Classifier: Programming Language :: Python :: 3
Requires-Python: >=3.6.7
Provides-Extra: dev
Requires-Dist: pytest; extra == 'dev'
Requires-Dist: pytest-asyncio; extra == 'dev'
Requires-Dist: pytest-cov; extra == 'dev'
